MANIFEST.in
README.md
setup.py
true_case/__init__.py
true_case/data.py
true_case/model.py
true_case/train.py
true_case.egg-info/PKG-INFO
true_case.egg-info/SOURCES.txt
true_case.egg-info/dependency_links.txt
true_case.egg-info/requires.txt
true_case.egg-info/top_level.txt
true_case/data/model.p